aisimplekit/__init__.py
aisimplekit/dnn/__init__.py
aisimplekit/dnn/embeddings.py
aisimplekit/dnn/rnn.py
aisimplekit/features/__init__.py
aisimplekit/features/stats.py
aisimplekit/features/tfidf.py
aisimplekit/models/__init__.py
aisimplekit/models/lgb.py
aisimplekit/models/xgb.py
aisimplekit-0.0.11.dist-info/LICENSE
aisimplekit-0.0.11.dist-info/METADATA
aisimplekit-0.0.11.dist-info/WHEEL
aisimplekit-0.0.11.dist-info/top_level.txt
aisimplekit-0.0.11.dist-info/RECORD
